polars_bin2/__init__.py
polars_bin2/expr_bin2.py
polars_bin2/series_bin2.py
polars_bin2-0.1.0.dist-info/LICENSE-APACHE
polars_bin2-0.1.0.dist-info/LICENSE-MIT
polars_bin2-0.1.0.dist-info/WHEEL
polars_bin2-0.1.0.dist-info/METADATA
polars_bin2-0.1.0.dist-info/RECORD
