Metadata-Version: 2.1
Name: polars_bin2
Version: 0.1.0
Summary: An enhanced `bin` namespace for polars
Requires-Python: >=3.7
Project-URL: Source, https://github.com/sslivkoff/polars_bin2
